plantuml_gentools/__init__.py
plantuml_gentools-0.1.2.dist-info/LICENSE
plantuml_gentools-0.1.2.dist-info/METADATA
plantuml_gentools-0.1.2.dist-info/WHEEL
plantuml_gentools-0.1.2.dist-info/top_level.txt
plantuml_gentools-0.1.2.dist-info/RECORD
