Metadata-Version: 2.1
Name: plantuml-gentools
Version: 0.1.2
Summary: PlantUML gen Tools.
Home-page: https://github.com/qeyup/plantuml_gentools.git
Author: Javier Moreno
Author-email: jgmore@gmail.com
License: UNKNOWN
Platform: UNKNOWN
Classifier: Programming Language :: Python :: 3
Classifier: License :: OSI Approved :: MIT License
Classifier: Operating System :: OS Independent
